egcst/__init__.py
egcst/core.py
egcst-0.0.12.dist-info/METADATA
egcst-0.0.12.dist-info/WHEEL
egcst-0.0.12.dist-info/top_level.txt
egcst-0.0.12.dist-info/RECORD
